[
  {"title":"SP","nextlevel":"partidos","dados2008":[    ,    ,1200],"dados2012":[,],"valorFinal2008":[26   ]},
  {"title":"MG","nextlevel":"partidos","dados2008":[    ,    ,1200],"dados2012":[,],"valorFinal2008":[14   ]},
  {"title":"RJ","nextlevel":"partidos","dados2008":[    ,    ,1200],"dados2012":[,],"valorFinal2008":[4    ]},
  {"title":"BA","nextlevel":"partidos","dados2008":[    ,    ,1200],"dados2012":[,],"valorFinal2008":[16   ]},
  {"title":"RS","nextlevel":"partidos","dados2008":[    ,    ,1200],"dados2012":[,],"valorFinal2008":[12   ]},
  {"title":"PR","nextlevel":"partidos","dados2008":[    ,    ,1200],"dados2012":[,],"valorFinal2008":[12   ]},
  {"title":"PE","nextlevel":"partidos","dados2008":[    ,    ,1200],"dados2012":[,],"valorFinal2008":[48   ]},
  {"title":"CE","nextlevel":"partidos","dados2008":[    ,    ,1200],"dados2012":[,],"valorFinal2008":[22   ]},
  {"title":"PA","nextlevel":"partidos","dados2008":[    ,    ,1200],"dados2012":[,],"valorFinal2008":[4    ]},
  {"title":"SC","nextlevel":"partidos","dados2008":[    ,    ,1200],"dados2012":[,],"valorFinal2008":[1    ]},
  {"title":"MA","nextlevel":"partidos","dados2008":[    ,    ,1200],"dados2012":[,],"valorFinal2008":[9    ]},
  {"title":"GO","nextlevel":"partidos","dados2008":[    ,    ,1200],"dados2012":[,],"valorFinal2008":[4    ]},
  {"title":"PB","nextlevel":"partidos","dados2008":[    ,    ,1200],"dados2012":[,],"valorFinal2008":[12   ]},
  {"title":"ES","nextlevel":"partidos","dados2008":[    ,    ,1200],"dados2012":[,],"valorFinal2008":[13   ]},
  {"title":"PI","nextlevel":"partidos","dados2008":[    ,    ,1200],"dados2012":[,],"valorFinal2008":[38   ]},
  {"title":"RN","nextlevel":"partidos","dados2008":[    ,    ,1200],"dados2012":[,],"valorFinal2008":[44   ]},
  {"title":"MT","nextlevel":"partidos","dados2008":[    ,    ,1200],"dados2012":[,],"valorFinal2008":[3    ]},
  {"title":"AL","nextlevel":"partidos","dados2008":[    ,    ,1200],"dados2012":[,],"valorFinal2008":[5    ]},
  {"title":"AM","nextlevel":"partidos","dados2008":[    ,    ,1200],"dados2012":[,],"valorFinal2008":[1    ]},
  {"title":"MS","nextlevel":"partidos","dados2008":[    ,    ,1200],"dados2012":[,],"valorFinal2008":[2    ]},
  {"title":"SE","nextlevel":"partidos","dados2008":[    ,    ,1200],"dados2012":[,],"valorFinal2008":[10   ]},
  {"title":"RO","nextlevel":"partidos","dados2008":[    ,    ,1200],"dados2012":[,],"valorFinal2008":[3    ]},
  {"title":"TO","nextlevel":"partidos","dados2008":[    ,    ,1200],"dados2012":[,],"valorFinal2008":[4    ]},
  {"title":"AC","nextlevel":"partidos","dados2008":[    ,    ,1200],"dados2012":[,],"valorFinal2008":[2    ]},
  {"title":"AP","nextlevel":"partidos","dados2008":[    ,    ,1200],"dados2012":[,],"valorFinal2008":[0    ]},
  {"title":"RR","nextlevel":"partidos","dados2008":[    ,    ,1200],"dados2012":[,],"valorFinal2008":[1    ]}
]




























